{
    "page_number": 4,
    "content": [
        {
            "label": "text",
            "x0": 83.93335469563802,
            "top": 469.4710693359375,
            "x1": 533.7703450520834,
            "bottom": 500.4329020182292,
            "score": 0.88,
            "page_number": 4
        },
        {
            "label": "text",
            "x0": 83.5575663248698,
            "top": 432.0499674479167,
            "x1": 532.0010172526041,
            "bottom": 462.435791015625,
            "score": 0.86,
            "page_number": 4
        },
        {
            "label": "text",
            "x0": 84.15534973144531,
            "top": 409.0545654296875,
            "x1": 192.77840169270834,
            "bottom": 424.3699544270833,
            "score": 0.83,
            "page_number": 4
        },
        {
            "label": "text",
            "x0": 83.63706461588542,
            "top": 385.8251139322917,
            "x1": 197.0098876953125,
            "bottom": 401.3604736328125,
            "score": 0.8,
            "page_number": 4
        },
        {
            "label": "figure",
            "x0": 89.6168924967448,
            "top": 114.61182657877605,
            "x1": 532.2859293619791,
            "bottom": 373.0845133463542,
            "score": 0.95,
            "page_number": 4
        },
        {
            "label": "figure",
            "x0": 83.69405619303386,
            "top": 55.65391540527344,
            "x1": 540.4337565104166,
            "bottom": 89.34801228841145,
            "score": 0.33,
            "page_number": 4
        },
        {
            "label": "table",
            "x0": 83.69405619303386,
            "top": 55.65391540527344,
            "x1": 540.4337565104166,
            "bottom": 89.34801228841145,
            "score": 0.63,
            "page_number": 4
        }
    ]
}